easyselect/__init__.py
easyselect-23.0.0.dist-info/METADATA
easyselect-23.0.0.dist-info/WHEEL
easyselect-23.0.0.dist-info/RECORD
