Metadata-Version: 2.1
Name: easyselect
Version: 23.0.0
Summary: simple and pretty tool for selecting items by keyboard in terminal
Project-URL: Homepage, https://github.com/gmankab/easyselect
Project-URL: Bug Tracker, https://github.com/gmankab/easyselect/issues
Project-URL: Documentation, https://github.com/gmankab/easyselect
Author-email: gmanka <gmankab@gmail.com>
Classifier: License :: OSI Approved :: GNU General Public License v3 (GPLv3)
Classifier: Operating System :: OS Independent
Classifier: Programming Language :: Python :: 3
Requires-Python: >=3.10
Requires-Dist: rich
Requires-Dist: windows-curses; platform_system == 'Windows'
